hanschunks-0.1.0.dist-info/METADATA
hanschunks-0.1.0.dist-info/WHEEL
hanschunks-0.1.0.dist-info/licenses/LICENSE
hanschunks/__init__.py
hanschunks/__init__.pyi
hanschunks/__pycache__/__init__.cpython-312.pyc
hanschunks/hanschunks.abi3.so
hanschunks/hanschunks.pyi
hanschunks-0.1.0.dist-info/RECORD
