Metadata-Version: 2.4
Name: hanschunks
Version: 0.1.0
Classifier: Programming Language :: Rust
Classifier: Programming Language :: Python :: 3
Classifier: License :: OSI Approved :: MIT License
Classifier: Operating System :: OS Independent
Requires-Dist: pdoc ; extra == 'docs'
Provides-Extra: docs
License-File: LICENSE
Summary: High-performance Chinese document extractor + semantic chunker
Author-email: atopx <3940422@qq.com>
License: MIT
Requires-Python: >=3.12
